02/02.v
module fulladder(a,b,cin,s,cout);
input a,b,cin;
output s,cout;
    assign s  = a ^ b ^ cin;
    assign cout = (a & b) | (b & cin) | (cin & a);
endmodule

02/testbench02.v
`timescale 1ms/1ms
module testbench02;
 reg a,b,cin;
 wire cout,s;
 fulladder fa(a,b,cin,s,cout);
 initial begin
  $dumpfile("tmp.vcd");
  $dumpvars();
  $monitor("%t %b %b %b %b %b",$time,a,b,cin,cout,s);
  #0   cin = 1'b0;a=1'b0;b=1'b0;
  #100 cin = 1'b0;a=1'b0;b=1'b1;
  #100 cin = 1'b0;a=1'b1;b=1'b0;
  #100 cin = 1'b0;a=1'b1;b=1'b1;
  #100 cin = 1'b1;a=1'b0;b=1'b0;
  #100 cin = 1'b1;a=1'b0;b=1'b1;
  #100 cin = 1'b1;a=1'b1;b=1'b0;
  #100 cin = 1'b1;a=1'b1;b=1'b1;
  #100 cin = 1'b0;a=1'b0;b=1'b0;

  #100 $finish;
 end 
endmodule

02/tmp.vcd
$date
	Tue May 26 14:26:08 2026
$end
$version
	Icarus Verilog
$end
$timescale
	1ms
$end
$scope module testbench02 $end
$var wire 1 ! s $end
$var wire 1 " cout $end
$var reg 1 # a $end
$var reg 1 $ b $end
$var reg 1 % cin $end
$scope module fa $end
$var wire 1 # a $end
$var wire 1 $ b $end
$var wire 1 % cin $end
$var wire 1 " cout $end
$var wire 1 ! s $end
$upscope $end
$upscope $end
$enddefinitions $end
$comment Show the parameter values. $end
$dumpall
$end
#0
$dumpvars
0%
0$
0#
0"
0!
$end
#100
1!
1$
#200
0$
1#
#300
1"
0!
1$
#400
0"
1!
0$
0#
1%
#500
1"
0!
1$
#600
0$
1#
#700
1!
1$
#800
0"
0!
0$
0#
0%
