04/04.v
module mux41(s1,s0,d3,d2,d1,d0,y);
input s1,s0,d3,d2,d1,d0;
output y;
 assign y = (~s1 & ~s0 & d0) | (~s1 & s0 & d1) | (s1 & ~ s0 & d2) | (s1 & s0 & d3);
endmodule

04/testbench04.v
`timescale 1ms/1ms
module testbench04;
 reg s1,s0,d3,d2,d1,d0;
 wire y;
 mux41 mux(s1,s0,d3,d2,d1,d0,y);
 initial begin
  $dumpfile("tmp.vcd");
  $dumpvars();
  $monitor("%t %b %b %b %b %b %b %b",$time,s1,s0,d3,d2,d1,d0,y);
  #0   s1 = 1'b0;s0 = 1'b0;d3 = 1'b0;d2 = 1'b0;d1 = 1'b0;d0 = 1'b0;
  #100 s1 = 1'b0;s0 = 1'b1;
  #100 s1 = 1'b1;s0 = 1'b0;
  #100 s1 = 1'b1;s0 = 1'b1;

  #100 s1 = 1'b0;s0 = 1'b0;d3 = 1'b0;d2 = 1'b0;d1 = 1'b0;d0 = 1'b1;
  #100 s1 = 1'b0;s0 = 1'b1;d3 = 1'b0;d2 = 1'b0;d1 = 1'b1;d0 = 1'b0;
  #100 s1 = 1'b1;s0 = 1'b0;d3 = 1'b0;d2 = 1'b1;d1 = 1'b0;d0 = 1'b0;
  #100 s1 = 1'b1;s0 = 1'b1;d3 = 1'b1;d2 = 1'b0;d1 = 1'b0;d0 = 1'b0;

  #100 s1 = 1'b0;s0 = 1'b0;d3 = 1'b0;d2 = 1'b0;d1 = 1'b0;d0 = 1'b0;
  
  #100 s1 = 1'b0;s0 = 1'b1;d3 = 1'b0;d2 = 1'b0;d1 = 1'b0;d0 = 1'b1;
  #100 s1 = 1'b0;s0 = 1'b1;d3 = 1'b0;d2 = 1'b0;d1 = 1'b1;d0 = 1'b0;
  #100 s1 = 1'b0;s0 = 1'b1;d3 = 1'b0;d2 = 1'b1;d1 = 1'b0;d0 = 1'b0;
  #100 s1 = 1'b0;s0 = 1'b1;d3 = 1'b1;d2 = 1'b0;d1 = 1'b0;d0 = 1'b0;
  
  #100 s1 = 1'b0;s0 = 1'b0;d3 = 1'b0;d2 = 1'b0;d1 = 1'b0;d0 = 1'b0;
  #100 $finish;
 end 
endmodule

04/tmp.vcd
$date
	Tue May 26 14:51:47 2026
$end
$version
	Icarus Verilog
$end
$timescale
	1ms
$end
$scope module testbench04 $end
$var wire 1 ! y $end
$var reg 1 " d0 $end
$var reg 1 # d1 $end
$var reg 1 $ d2 $end
$var reg 1 % d3 $end
$var reg 1 & s0 $end
$var reg 1 ' s1 $end
$scope module mux $end
$var wire 1 " d0 $end
$var wire 1 # d1 $end
$var wire 1 $ d2 $end
$var wire 1 % d3 $end
$var wire 1 & s0 $end
$var wire 1 ' s1 $end
$var wire 1 ! y $end
$upscope $end
$upscope $end
$enddefinitions $end
$comment Show the parameter values. $end
$dumpall
$end
#0
$dumpvars
0'
0&
0%
0$
0#
0"
0!
$end
#100
1&
#200
0&
1'
#300
1&
#400
1!
1"
0&
0'
#500
0"
1#
1&
#600
0#
1$
0&
1'
#700
0$
1%
1&
#800
0!
0%
0&
0'
#900
0!
1"
1&
#1000
1!
0"
1#
#1100
0!
0#
1$
#1200
0$
1%
#1300
0%
0&
