03/03.v
module demux14(d,s1,s0,y3,y2,y1,y0);
input d,s1,s0;
output y3,y2,y1,y0;
 assign y3 = d & s1 & s0;
 assign y2 = d & s1 & (~s0);
 assign y1 = d & (~s1) & s0;
 assign y0 = d & (~s1) & (~s0);
endmodule

03/testbench03.v
`timescale 1ms/1ms
module testbench03;
 reg d,s1,s0;
 wire y3,y2,y1,y0;
 demux14 demux(d,s1,s0,y3,y2,y1,y0);
 initial begin
  $dumpfile("tmp.vcd");
  $dumpvars();
  $monitor("%t %b %b %b %b %b %b %b",$time,d,s1,s0,y3,y2,y1,y0);
  #0   d=1'b0;s1=1'b0;s0=1'b0;
  #100 d=1'b0;s1=1'b0;s0=1'b1;
  #100 d=1'b0;s1=1'b1;s0=1'b0;
  #100 d=1'b0;s1=1'b1;s0=1'b1;
  #100 d=1'b1;s1=1'b0;s0=1'b0;
  #100 d=1'b1;s1=1'b0;s0=1'b1;
  #100 d=1'b1;s1=1'b1;s0=1'b0;
  #100 d=1'b1;s1=1'b1;s0=1'b1;
  #100 d=1'b0;s1=1'b0;s0=1'b0;
  #100 $finish;
 end 
endmodule

03/tmp.vcd
$date
	Tue May 26 14:36:46 2026
$end
$version
	Icarus Verilog
$end
$timescale
	1ms
$end
$scope module testbench03 $end
$var wire 1 ! y3 $end
$var wire 1 " y2 $end
$var wire 1 # y1 $end
$var wire 1 $ y0 $end
$var reg 1 % d $end
$var reg 1 & s0 $end
$var reg 1 ' s1 $end
$scope module demux $end
$var wire 1 % d $end
$var wire 1 & s0 $end
$var wire 1 ' s1 $end
$var wire 1 $ y0 $end
$var wire 1 # y1 $end
$var wire 1 " y2 $end
$var wire 1 ! y3 $end
$upscope $end
$upscope $end
$enddefinitions $end
$comment Show the parameter values. $end
$dumpall
$end
#0
$dumpvars
0'
0&
0%
0$
0#
0"
0!
$end
#100
1&
#200
0&
1'
#300
1&
#400
1$
0&
0'
1%
#500
0$
1#
1&
#600
1"
0#
0&
1'
#700
0"
1!
1&
#800
0!
0&
0'
0%
