05/05.v
module priority_encoder(x0,x1,x2,x3,x4,x5,x6,x7,b0,b1,b2);

    input x0,x1,x2,x3,x4,x5,x6,x7;
    output b0,b1,b2;

    assign b0 = ~x6 & (~x4 & ~x2 & x1 | ~x4 & x3 | x5) | x7;
    assign b1 = ~x5 & ~x4 & (x2 | x3) | x6 | x7;
    assign b2 = x4 | x5 | x6 | x7;

endmodule

05/testbench05.v
`timescale 1ms/1ms
module testbench05;
 reg x0,x1,x2,x3,x4,x5,x6,x7;
 wire b0,b1,b2;
 priority_encoder pe(x0,x1,x2,x3,x4,x5,x6,x7,b0,b1,b2);
 initial begin
  $dumpfile("tmp.vcd");
  $dumpvars();
  $monitor("%t %b %b %b %b %b %b %b %b %b %b %b",$time,x0,x1,x2,x3,x4,x5,x6,x7,b0,b1,b2);
  #0   x7 = 1'b0;x6 = 1'b0;x5 = 1'b0;x4 = 1'b0;x3 = 1'b0;x2 = 1'b0;x1 = 1'b0;x0 = 1'b0;
  #100 x7 = 1'b1;
  #100 x7 = 1'b0; x6 = 1'b1;
  #100 x6 = 1'b0; x5 = 1'b1;
  #100 x5 = 1'b0; x4 = 1'b1;
  #100 x4 = 1'b0; x3 = 1'b1;
  #100 x3 = 1'b0; x2 = 1'b1;
  #100 x2 = 1'b0; x1 = 1'b1;
  #100 x1 = 1'b0; x0 = 1'b1;

  #100 x7 = 1'b1;x6 = 1'b1;x5 = 1'b1;x4 = 1'b1;x3 = 1'b1;x2 = 1'b1;x1 = 1'b1;x0 = 1'b1;
  #100 x7 = 1'b0;
  #100 x6 = 1'b0;
  #100 x5 = 1'b0;
  #100 x4 = 1'b0;
  #100 x3 = 1'b0;
  #100 x2 = 1'b0;
  #100 x1 = 1'b0;
  #100 x0 = 1'b0;

  #100 $finish;
 end 
endmodule

05/tmp.vcd
$date
	Sat May 30 13:49:43 2026
$end
$version
	Icarus Verilog
$end
$timescale
	1ms
$end
$scope module testbench05 $end
$var wire 1 ! b2 $end
$var wire 1 " b1 $end
$var wire 1 # b0 $end
$var reg 1 $ x0 $end
$var reg 1 % x1 $end
$var reg 1 & x2 $end
$var reg 1 ' x3 $end
$var reg 1 ( x4 $end
$var reg 1 ) x5 $end
$var reg 1 * x6 $end
$var reg 1 + x7 $end
$scope module pe $end
$var wire 1 # b0 $end
$var wire 1 " b1 $end
$var wire 1 ! b2 $end
$var wire 1 $ x0 $end
$var wire 1 % x1 $end
$var wire 1 & x2 $end
$var wire 1 ' x3 $end
$var wire 1 ( x4 $end
$var wire 1 ) x5 $end
$var wire 1 * x6 $end
$var wire 1 + x7 $end
$upscope $end
$upscope $end
$enddefinitions $end
$comment Show the parameter values. $end
$dumpall
$end
#0
$dumpvars
0+
0*
0)
0(
0'
0&
0%
0$
0#
0"
0!
$end
#100
1#
1"
1!
1+
#200
0#
1"
1!
1*
0+
#300
1#
0"
1!
1)
0*
#400
0#
1(
0)
#500
1#
1"
0!
1'
0(
#600
0#
1&
0'
#700
1#
0"
1%
0&
#800
0#
1$
0%
#900
1#
1"
1!
1%
1&
1'
1(
1)
1*
1+
#1000
0#
0+
#1100
1#
0"
0*
#1200
0#
0)
#1300
1#
1"
0!
0(
#1400
0#
0'
#1500
1#
0"
0&
#1600
0#
0%
#1700
0$
