06/06.v
module decoder38(b2,b1,b0,y0,y1,y2,y3,y4,y5,y6,y7);

    input b0,b1,b2;
    output y0,y1,y2,y3,y4,y5,y6,y7;

    assign y0 = ~b2 & ~b1 & ~b0;
    assign y1 = ~b2 & ~b1 & b0;
    assign y2 = ~b2 & b1 & ~b0;
    assign y3 = ~b2 & b1 & b0;
    assign y4 = b2 & ~b1 & ~b0;
    assign y5 = b2 & ~b1 & b0;
    assign y6 = b2 & b1 & ~b0;
    assign y7 = b2 & b1 & b0;


endmodule

06/testbench06.v
`timescale 1ms/1ms
module testbench06;
 reg b0,b1,b2;
 wire y0,y1,y2,y3,y4,y5,y6,y7;
 decoder38 de(b2,b1,b0,y0,y1,y2,y3,y4,y5,y6,y7);
 initial begin
  $dumpfile("tmp.vcd");
  $dumpvars();
  $monitor("%t %b %b %b %b %b %b %b %b %b %b %b",$time,b2,b1,b0,y0,y1,y2,y3,y4,y5,y6,y7);
    #0   b2 = 1'b0;b1 = 1'b0;b0 = 1'b0;
    #100 b2 = 1'b1;b1 = 1'b1;b0 = 1'b1;
    #100 b2 = 1'b1;b1 = 1'b1;b0 = 1'b0;
    #100 b2 = 1'b1;b1 = 1'b0;b0 = 1'b1;
    #100 b2 = 1'b1;b1 = 1'b0;b0 = 1'b0;
    #100 b2 = 1'b0;b1 = 1'b1;b0 = 1'b1;
    #100 b2 = 1'b0;b1 = 1'b1;b0 = 1'b0;
    #100 b2 = 1'b0;b1 = 1'b0;b0 = 1'b1;
    #100 b2 = 1'b0;b1 = 1'b0;b0 = 1'b0;

  #100 $finish;
 end 
endmodule

06/tmp.vcd
$date
	Sat May 30 14:02:14 2026
$end
$version
	Icarus Verilog
$end
$timescale
	1ms
$end
$scope module testbench06 $end
$var wire 1 ! y7 $end
$var wire 1 " y6 $end
$var wire 1 # y5 $end
$var wire 1 $ y4 $end
$var wire 1 % y3 $end
$var wire 1 & y2 $end
$var wire 1 ' y1 $end
$var wire 1 ( y0 $end
$var reg 1 ) b0 $end
$var reg 1 * b1 $end
$var reg 1 + b2 $end
$scope module de $end
$var wire 1 ) b0 $end
$var wire 1 * b1 $end
$var wire 1 + b2 $end
$var wire 1 ( y0 $end
$var wire 1 ' y1 $end
$var wire 1 & y2 $end
$var wire 1 % y3 $end
$var wire 1 $ y4 $end
$var wire 1 # y5 $end
$var wire 1 " y6 $end
$var wire 1 ! y7 $end
$upscope $end
$upscope $end
$enddefinitions $end
$comment Show the parameter values. $end
$dumpall
$end
#0
$dumpvars
0+
0*
0)
1(
0'
0&
0%
0$
0#
0"
0!
$end
#100
0(
0'
0#
1!
1)
1*
1+
#200
1"
0!
0)
#300
1#
0"
1)
0*
#400
1$
0#
0)
#500
0$
1%
1)
1*
0+
#600
1&
0%
0)
#700
1'
0&
1)
0*
#800
1(
0'
0)
